runmd/__init__.py
runmd/cli.py
runmd/clishell.py
runmd/commands.py
runmd/config.ini
runmd/config.py
runmd/envmanager.py
runmd/history.py
runmd/parser.py
runmd/process.py
runmd/runner.py
runmd/vault.py
runmd-0.16.0.dist-info/LICENSE
runmd-0.16.0.dist-info/METADATA
runmd-0.16.0.dist-info/WHEEL
runmd-0.16.0.dist-info/entry_points.txt
runmd-0.16.0.dist-info/top_level.txt
runmd-0.16.0.dist-info/RECORD
