Metadata-Version: 2.1
Name: runmd
Version: 0.16.0
Summary: A CLI tool to run or list code blocks from Markdown files.
Author-email: Damien Pageot <damien.pageot+runmd@gmail.com>
License: MIT
Project-URL: Homepage, https://github.com/pageotd/runmd
Classifier: Programming Language :: Python :: 3
Classifier: License :: OSI Approved :: MIT License
Classifier: Operating System :: OS Independent
Requires-Python: >=3.9
License-File: LICENSE
Requires-Dist: pygments
Requires-Dist: cryptography
Requires-Dist: python-dotenv
Provides-Extra: dev
Requires-Dist: pytest; extra == "dev"
Requires-Dist: black; extra == "dev"
Requires-Dist: isort; extra == "dev"
Requires-Dist: flake8; extra == "dev"
Requires-Dist: pytest-cov; extra == "dev"
Provides-Extra: docs
Requires-Dist: mkdocs-material; extra == "docs"
